AUTHORS.md
LICENSE
MANIFEST.in
README.md
README.rst
setup.cfg
setup.py
django_sage_painless.egg-info/PKG-INFO
django_sage_painless.egg-info/SOURCES.txt
django_sage_painless.egg-info/dependency_links.txt
django_sage_painless.egg-info/requires.txt
django_sage_painless.egg-info/top_level.txt
kernel/__init__.py
kernel/asgi.py
kernel/settings.py
kernel/urls.py
kernel/wsgi.py
products/__init__.py
products/admin.py
products/apps.py
products/mixins.py
products/services.py
products/signals.py
products/views.py
products/migrations/0001_initial.py
products/migrations/0002_auto_20210724_1644.py
products/migrations/0003_auto_20210729_1317.py
products/migrations/0004_alter_discount_product.py
products/migrations/0005_alter_discount_product.py
products/migrations/0006_product_video.py
products/migrations/0007_remove_product_video.py
products/migrations/__init__.py
products/models/__init__.py
products/models/category.py
products/models/discount.py
products/models/product.py
products/tests/__init__.py
products/tests/test_category.py
products/tests/test_discount.py
products/tests/test_product.py
sage_painless/__init__.py
sage_painless/apps.py
sage_painless/classes/__init__.py
sage_painless/classes/admin.py
sage_painless/classes/field.py
sage_painless/classes/model.py
sage_painless/classes/signal.py
sage_painless/management/__init__.py
sage_painless/management/commands/__init__.py
sage_painless/management/commands/deploy.py
sage_painless/management/commands/docs.py
sage_painless/management/commands/generate.py
sage_painless/management/commands/validate_diagram.py
sage_painless/services/__init__.py
sage_painless/services/abstract.py
sage_painless/services/admin_generator.py
sage_painless/services/api_generator.py
sage_painless/services/base.py
sage_painless/services/constants.py
sage_painless/services/docker_generator.py
sage_painless/services/gunicorn_generator.py
sage_painless/services/model_generator.py
sage_painless/services/nginx_generator.py
sage_painless/services/readme_generator.py
sage_painless/services/test_generator.py
sage_painless/services/tox_generator.py
sage_painless/services/uwsgi_generator.py
sage_painless/templates/Dockerfile.jinja
sage_painless/templates/README.jinja
