Metadata-Version: 2.1
Name: django-sage-painless
Version: 1.14.3
Summary: A handy tool for generating Django-based backend projects without coding. On the other hand, it is a code generator of the Django framework.
Home-page: https://github.com/sageteam-org/django-sage-painless
Author: Sage Team
Author-email: mail@sageteam.org
License: GNU
Download-URL: https://github.com/sageteam-org/django-sage-painless/archive/refs/tags/1.5.0.tar.gz
Keywords: django,python,generate,code generator,django rest framework,nginx,redis,rabbitmq,docker,gunicorn,automation
Platform: UNKNOWN
Classifier: Environment :: Web Environment
Classifier: Framework :: Django
Classifier: Framework :: Django :: 3.1
Classifier: Framework :: Django :: 3.2
Classifier: Intended Audience :: Developers
Classifier: License :: OSI Approved :: GNU Affero General Public License v3
Classifier: Operating System :: OS Independent
Classifier: Programming Language :: Python
Classifier: Programming Language :: Python :: 3
Classifier: Programming Language :: Python :: 3 :: Only
Classifier: Programming Language :: Python :: 3.6
Classifier: Programming Language :: Python :: 3.7
Classifier: Programming Language :: Python :: 3.8
Classifier: Programming Language :: Python :: 3.9
Classifier: Topic :: Internet :: WWW/HTTP
Classifier: Topic :: Internet :: WWW/HTTP :: Dynamic Content
Requires-Python: >=3.8
